<?xml version="1.0" encoding="utf-8" ?>
<odoo>
    <data>
        <record id="action_hospital_doctor_visit_tree_view" model="ir.ui.view">
            <field name="name">hospital.doctor_visit.tree</field>
            <field name="model">hospital.doctor_visit</field>
            <field name="arch" type="xml">
                <tree>
                    <field name="doctor"/>
                    <field name="patient"/>
                    <field name="appointment_date"/>
                    <field name="time_slot"/>
                </tree>
            </field>
         </record>
        <record id="action_hospital_doctor_visit_form_view" model="ir.ui.view">
            <field name="name">hospital.doctor_visit.form</field>
            <field name="model">hospital.doctor_visit</field>
            <field name="arch" type="xml">
                <form>
                    <header>
                        <button string="Finish Research" type="object" name="action_finish_research" class="btn btn-primary" invisible ="state != 'add_research'"/>
                        <button string="Skip Research" type="object" name="action_skip_research" class="btn btn-danger" invisible ="state != 'new'"/>

                        <button string="Finish Diagnosis" type="object" name="action_finish_diagnosis" class="btn btn-primary" invisible ="state != 'make_diagnosis'"/>
                        <button string="Skip Diagnosis" type="object" name="action_skip_diagnosis" class="btn btn-danger" invisible ="state != 'confirm_research'"/>
                        <field name="state" widget="statusbar"/>
                    </header>
                    <sheet>
                        <group>
                            <field name="doctor" readonly="state != 'create'"/>
                            <field name="patient" readonly="state != 'create'"/>
                            <field name="appointment_date" readonly="state != 'create'"/>
                            <field name="time_slot" widget="select" readonly="state != 'create'"/>
                            <field name="is_completed"/>
                        </group>
                        <notebook>
                            <page string="Research">
                                <field name="research_ids">
                                    <tree editable="bottom" decoration-success="status_research == 'accepted_research'" decoration-danger="status_research == 're-research'">
                                        <field name="doctor" invisible="1" column_invisible="1"/>
                                        <field name="patient" invisible="1" column_invisible="1"/>
                                        <field name="research_type" readonly="status_research in ['accepted_research'],"/>
                                        <field name="sample_type" readonly="status_research in ['accepted_research'],"/>
                                        <field name="conclusions" widget="text" readonly="status_research in ['accepted_research'],"/>
                                        <field name="status_research" readonly="1"/>
                                        <button name="action_accept_research" type="object" icon="fa-check" string="Accept" invisible="status_research in ['accepted_research']"/>
                                        <button name="action_decline_research" type="object" icon="fa-times" string="Re-research" invisible="status_research in ['accepted_research']"/>
                                    </tree>
                                </field>
                            </page>
                            <page string="Diagnosis">
                                <field name="diagnosis_ids">
                                    <tree editable="bottom" decoration-success="status_diagnosis == 'accepted_diagnosis'" decoration-danger="status_diagnosis == 'reconsider'">
                                        <field name="doctor" invisible="1" column_invisible="1"/>
                                        <field name="patient" invisible="1" column_invisible="1"/>
                                        <field name="disease" readonly="status_diagnosis in ['accepted_diagnosis'],"/>
                                        <field name="treatment" readonly="status_diagnosis in ['accepted_diagnosis'],"/>
                                        <field name="diagnosis_date" readonly="status_diagnosis in ['accepted_diagnosis'],"/>
                                        <field name="research_ids" readonly="status_diagnosis in ['accepted_diagnosis'],"/>
                                        <field name="mentor_comment" readonly="status_diagnosis in ['accepted_diagnosis'],"/>
                                        <field name="status_diagnosis" readonly="1"/>
                                         <button name="action_accept_diagnosis" type="object" icon="fa-check" string="Accept"/>
                                        <button name="action_reconsider_diagnosis" type="object" icon="fa-times" string="Reconsider"/>
                                    </tree>
                                </field>
                            </page>
                            <page string="Recommendations">
                                <group>
                                    <field name="recommendations"/>
                                </group>
                            </page>
                        </notebook>
                    </sheet>
                </form>
            </field>
        </record>
        <record id="action_hospital_doctor_visit" model="ir.actions.act_window">
            <field name="name">Doctor Visit</field>
            <field name="res_model">hospital.doctor_visit</field>
            <field name="view_mode">tree,form</field>
            <field name="view_id" ref="action_hospital_doctor_visit_tree_view"/>
            <field name="help" type="html">
                <p class="o_view_noconten_smiling_face">
                        Create a new visit to doctor
                </p>
            </field>
        </record>
    </data>
</odoo>